numericals/__init__.py
numericals/integrate.py
numericals/ode.py
numericals/optimize.py
numericals/root.py
numericals-0.4.1.dist-info/licenses/LICENSE
numericals-0.4.1.dist-info/METADATA
numericals-0.4.1.dist-info/WHEEL
numericals-0.4.1.dist-info/top_level.txt
numericals-0.4.1.dist-info/RECORD
