Metadata-Version: 2.4
Name: numericals
Version: 0.4.1
Summary: Numerical methods in pure python
Author: Andrew Yoo
License-Expression: LGPL-3.0-or-later
Project-URL: Repository, https://github.com/andrew-yoo/numericals
Requires-Python: >=3.13
License-File: LICENSE
Provides-Extra: dev
Requires-Dist: pdoc3>=0.11.6; extra == "dev"
Requires-Dist: pytest>=9.0.0; extra == "dev"
Dynamic: license-file
